cfde_submit/__init__.py
cfde_submit/bdbag_utils.py
cfde_submit/client.py
cfde_submit/config.py
cfde_submit/exc.py
cfde_submit/globus_http.py
cfde_submit/main.py
cfde_submit/validation.py
cfde_submit/version.py
cfde_submit-0.2.5.dist-info/LICENSE
cfde_submit-0.2.5.dist-info/METADATA
cfde_submit-0.2.5.dist-info/WHEEL
cfde_submit-0.2.5.dist-info/entry_points.txt
cfde_submit-0.2.5.dist-info/top_level.txt
cfde_submit-0.2.5.dist-info/RECORD
