Metadata-Version: 2.1
Name: cfde-submit
Version: 0.2.5
Summary: A command line tool for submitting CFDE Datasets
Home-page: https://github.com/nih-cfde/cfde-submit
Maintainer: CFDE
Maintainer-email: david@globus.org
License: Apache 2.0
Platform: UNKNOWN
Classifier: Intended Audience :: Science/Research
Classifier: Intended Audience :: Developers
Classifier: License :: OSI Approved :: Apache Software License
Classifier: Operating System :: POSIX
Classifier: Operating System :: MacOS :: MacOS X
Classifier: Programming Language :: Python
Classifier: Programming Language :: Python :: 3.6
Classifier: Programming Language :: Python :: 3.7
Classifier: Programming Language :: Python :: 3.8
Classifier: Programming Language :: Python :: 3.9
Requires-Python: >=3.6
Requires-Dist: GitPython (>=3.0.4)
Requires-Dist: PyYAML (<6.0.0,>=5.3.1)
Requires-Dist: bdbag (>=1.6.0)
Requires-Dist: click (==7.1.1)
Requires-Dist: fair-research-login (==0.2.6)
Requires-Dist: frictionless (==4.16.2)
Requires-Dist: globus-automate-client (==0.12.2)
Requires-Dist: globus-sdk (<3.0,>=2.0)
Requires-Dist: jsonschema (<4.0.0,>=3.2.0)
Requires-Dist: packaging (>=20.1)
Requires-Dist: requests (>=2.22.0)
Requires-Dist: typer[all] (<0.4.0,>=0.3.0)
